pyVim/__init__.py
pyVim/connect.py
pyVim/sso.py
pyVim/task.py
pyVmomi/Cache.py
pyVmomi/CoreTypes.py
pyVmomi/Differ.py
pyVmomi/DynamicTypeManagerHelper.py
pyVmomi/EamObjects.py
pyVmomi/Iso8601.py
pyVmomi/ManagedMethodExecutorHelper.py
pyVmomi/PbmObjects.py
pyVmomi/QueryTypes.py
pyVmomi/ServerObjects.py
pyVmomi/SmsObjects.py
pyVmomi/SoapAdapter.py
pyVmomi/StubAdapterAccessorImpl.py
pyVmomi/Version.py
pyVmomi/VmomiSupport.py
pyVmomi/__init__.py
pyVmomi/pyVmomiSettings.py
pyvmomi-6.5.dist-info/DESCRIPTION.rst
pyvmomi-6.5.dist-info/METADATA
pyvmomi-6.5.dist-info/RECORD
pyvmomi-6.5.dist-info/WHEEL
pyvmomi-6.5.dist-info/metadata.json
pyvmomi-6.5.dist-info/top_level.txt
pyvmomi-6.5.dist-info/zip-safe
