Metadata-Version: 2.0
Name: pyvmomi
Version: 6.5
Summary: VMware vSphere Python SDK
Home-page: https://github.com/vmware/pyvmomi
Author: VMware, Inc.
Author-email: jhu@vmware.com
License: License :: OSI Approved :: Apache Software License
Keywords: pyvmomi vsphere vmware esx
Platform: Windows
Platform: Linux
Platform: Solaris
Platform: Mac OS-X
Platform: Unix
Classifier: Development Status :: 5 - Production/Stable
Classifier: License :: OSI Approved :: Apache Software License
Classifier: Intended Audience :: Information Technology
Classifier: Intended Audience :: System Administrators
Classifier: Intended Audience :: Developers
Classifier: Environment :: No Input/Output (Daemon)
Classifier: Programming Language :: Python :: 2
Classifier: Programming Language :: Python :: 2.7
Classifier: Programming Language :: Python :: 3
Classifier: Programming Language :: Python :: 3.3
Classifier: Programming Language :: Python :: 3.4
Classifier: Programming Language :: Python :: 3.5
Classifier: Topic :: Software Development :: Libraries :: Python Modules
Classifier: Topic :: System :: Distributed Computing
Classifier: Operating System :: Microsoft :: Windows
Classifier: Operating System :: POSIX
Classifier: Operating System :: Unix
Classifier: Operating System :: MacOS
Requires-Dist: lxml
Requires-Dist: pyOpenSSL (>=0.14)
Requires-Dist: requests (>=2.3.0)
Requires-Dist: six (>=1.7.3)
